website_price_notifier/__init__.py
website_price_notifier/__main__.py
website_price_notifier/utils.py
website_price_notifier-1.1.2.dist-info/METADATA
website_price_notifier-1.1.2.dist-info/WHEEL
website_price_notifier-1.1.2.dist-info/entry_points.txt
website_price_notifier-1.1.2.dist-info/RECORD
