Metadata-Version: 2.4
Name: website-price-notifier
Version: 1.1.2
Summary: A program that scraps websites for prices and notifies you about it.
Author-email: en <enqiao2009@gmail.com>
Requires-Python: >=3.11
Requires-Dist: httpx>=0.28.1
Requires-Dist: schedule>=1.2.2
Requires-Dist: selenium>=4.34.0
Requires-Dist: webdriver-manager>=4.0.2
